.gitignore
LICENSE
NOTICE
README.rst
requirements.txt
setup.py
examples/generate_data.py
examples/generate_diatomic.py
examples/plotter.py
examples/pyscf_demo.ipynb
fermilibpluginpyscf/__init__.py
fermilibpluginpyscf/_run_pyscf.py
fermilibpluginpyscf/_version.py
fermilibpluginpyscf.egg-info/PKG-INFO
fermilibpluginpyscf.egg-info/SOURCES.txt
fermilibpluginpyscf.egg-info/dependency_links.txt
fermilibpluginpyscf.egg-info/requires.txt
fermilibpluginpyscf.egg-info/top_level.txt