Metadata-Version: 1.0
Name: fermilibpluginpyscf
Version: 0.1a0
Summary: A plugin allowing FermiLib to interface with PySCF.
Home-page: http://www.projectq.ch
Author: FermiLib plugin PySCF developers
Author-email: fermilib@projectq.ch
License: Apache 2
Platform: UNKNOWN
